openfund/__main__.py
openfund/__version__.py
openfund/binance_tools/__init__.py
openfund/binance_tools/common.py
openfund/binance_tools/continuous_klines.py
openfund/config/__init__.py
openfund/config/config.py
openfund/config/config_source.py
openfund/config/dict_config_source.py
openfund/config/file_config_source.py
openfund/config/source.py
openfund/config.ini
openfund/console/__init__.py
openfund/console/application.py
openfund/console/clogs/__init__.py
openfund/console/clogs/file_formatter.py
openfund/console/clogs/file_handler.py
openfund/console/clogs/filters.py
openfund/console/clogs/formatters/__init__.py
openfund/console/clogs/formatters/builder_formatter.py
openfund/console/clogs/formatters/formatter.py
openfund/console/clogs/io_formatter.py
openfund/console/clogs/io_handler.py
openfund/console/command_loader.py
openfund/console/commands/__init__.py
openfund/console/commands/about.py
openfund/console/commands/add.py
openfund/console/commands/build.py
openfund/console/commands/cache/__init__.py
openfund/console/commands/cache/clear.py
openfund/console/commands/cache/list.py
openfund/console/commands/check.py
openfund/console/commands/command.py
openfund/console/commands/config.py
openfund/console/commands/debug/__init__.py
openfund/console/commands/debug/info.py
openfund/console/commands/debug/resolve.py
openfund/console/commands/env_command.py
openfund/console/commands/export.py
openfund/console/commands/group_command.py
openfund/console/commands/init.py
openfund/console/commands/install.py
openfund/console/commands/installer_command.py
openfund/console/commands/lock.py
openfund/console/commands/new.py
openfund/console/commands/publish.py
openfund/console/commands/remove.py
openfund/console/commands/run.py
openfund/console/commands/search.py
openfund/console/commands/self/__init__.py
openfund/console/commands/self/add.py
openfund/console/commands/self/install.py
openfund/console/commands/self/lock.py
openfund/console/commands/self/remove.py
openfund-0.1.6.dist-info/LICENSE
openfund-0.1.6.dist-info/METADATA
openfund-0.1.6.dist-info/WHEEL
openfund-0.1.6.dist-info/entry_points.txt
openfund-0.1.6.dist-info/RECORD
