Metadata-Version: 2.1
Name: openfund
Version: 0.1.6
Summary: 
Author: yang99love
Author-email: yang99love@hotmail.com
Requires-Python: >=3.8,<4.0
Classifier: Programming Language :: Python :: 3
Classifier: Programming Language :: Python :: 3.8
Classifier: Programming Language :: Python :: 3.9
Classifier: Programming Language :: Python :: 3.10
Classifier: Programming Language :: Python :: 3.11
Classifier: Programming Language :: Python :: 3.12
Classifier: Programming Language :: Python :: 3.13
Requires-Dist: build (>=1.0.3,<2.0.0)
Requires-Dist: cachecontrol[filecache] (>=0.14.0,<0.15.0)
Requires-Dist: cleo (>=2.1.0,<3.0.0)
Requires-Dist: crashtest (>=0.4.1,<0.5.0)
Requires-Dist: dulwich (>=0.21.2,<0.22.0)
Requires-Dist: fastjsonschema (>=2.18.0,<3.0.0)
Requires-Dist: importlib-metadata (>=4.4) ; python_version < "3.10"
Requires-Dist: installer (>=0.7.0,<0.8.0)
Requires-Dist: keyring (>=24.0.0,<25.0.0)
Requires-Dist: packaging (>=23.1)
Requires-Dist: pexpect (>=4.7.0,<5.0.0)
Requires-Dist: pkginfo (>=1.10,<2.0)
Requires-Dist: platformdirs (>=3.0.0,<5)
Requires-Dist: poetry-core (==1.9.1)
Requires-Dist: poetry-plugin-export (>=1.6.0,<2.0.0)
Requires-Dist: pyproject-hooks (>=1.0.0,<2.0.0)
Requires-Dist: requests (>=2.26,<3.0)
Requires-Dist: requests-toolbelt (>=1.0.0,<2.0.0)
Requires-Dist: shellingham (>=1.5,<2.0)
Requires-Dist: simplejson (>=3.19.3,<4.0.0)
Requires-Dist: tomli (>=2.0.1,<3.0.0) ; python_version < "3.11"
Requires-Dist: tomlkit (>=0.11.4,<1.0.0)
Requires-Dist: trove-classifiers (>=2022.5.19)
Requires-Dist: virtualenv (>=20.26.6,<21.0.0)
Requires-Dist: xattr (>=1.0.0,<2.0.0) ; sys_platform == "darwin"
